setup.py
dg_integration.egg-info/PKG-INFO
dg_integration.egg-info/SOURCES.txt
dg_integration.egg-info/dependency_links.txt
dg_integration.egg-info/requires.txt
dg_integration.egg-info/top_level.txt
intellij/__init__.py
intellij/dgapi/__init__.py
intellij/dgapi/client.py
intellij/dgapi/connection.py
intellij/dgapi/cursor.py
intellij/dgapi/exceptions.py
intellij/dgapi/types.py
test/test.py