Metadata-Version: 1.0
Name: dg-integration
Version: 0.0.2
Summary: Implementation of DBAPI v2 on the top of DataGrip
Home-page: UNKNOWN
Author: Alexander Kass
Author-email: UNKNOWN
License: MIT
Keywords: IntelliJ IDEA DataGrip PhpStorm PyCharm GoLand
Platform: UNKNOWN
